rom/data_rom_reg.v
// 普通的数据rom，容量64 * 16b
    module data_rom_reg (
        clk,    // 时钟
        rst_n,  // 复位
        write_en,
        addr,   // 目标地址
        data_in,
        data_out,    // 取出的数据
    );

        input clk;
        input rst_n;
        input write_en;
        input [5: 0] addr;
        input [15: 0] data_in;
        output [15: 0] data_out;


        reg[15: 0] rom[63: 0]; // 用于存储读到的数据
        initial $readmemb("./init_data_reg.txt", rom, 0, 15);

        always @(posedge clk) begin
            if (write_en)
                rom[addr] <= data_in;
        end 

        assign data_out = rom[addr];

    endmodule

// 加强的的数据rom，容量512 * 16b
    module data_rom_reg_pro_max_ultra (
        clk,    // 时钟
        rst_n,  // 复位
        write_en,
        addr,   // 目标地址
        data_in,
        data_out,    // 取出的数据
    );

        input clk;
        input rst_n;
        input write_en;
        input [8: 0] addr;
        input [15: 0] data_in;
        output [15: 0] data_out;


        reg[15: 0] rom[511: 0]; // 用于存储读到的数据
        initial $readmemb("./init_data_reg.txt", rom, 0, 15);

        always @(posedge clk) begin
            if (write_en)
                rom[addr] <= data_in;
        end 

        assign data_out = rom[addr];

    endmodule

rom/data_rom_reg_test.v

`include "./rom/data_rom_reg.v"

module data_rom_reg_test ();
    
    wire [15: 0] data;

    reg [7: 0] addr;

    // data_rom_reg U_data_rom_reg(
    //     .addr(addr),
    //     .data(data)
    // );
    reg [7: 0] i;

    initial begin
        addr = 8'd0;
    end

    initial begin
        #10
        for (i = 0; i < 8'd8; i = i + 1) 
            #1
            addr = i;

        #10
        $finish;
    end
    initial begin            
        $dumpfile("./rom/data_rom_reg_test.vcd");      
        $dumpvars(0, data_rom_reg_test);   
    end

endmodule

rom/data_rom_reg_test.vcd
$date
	Sun May 21 13:56:29 2023
$end
$version
	Icarus Verilog
$end
$timescale
	1s
$end
$scope module data_rom_reg_test $end
$var wire 16 ! data [15:0] $end
$var reg 8 " addr [7:0] $end
$var reg 8 # i [7:0] $end
$scope module U_data_rom_reg $end
$var wire 8 $ addr [7:0] $end
$var wire 16 % data [15:0] $end
$upscope $end
$upscope $end
$enddefinitions $end
$comment Show the parameter values. $end
$dumpall
$end
#0
$dumpvars
b0 %
b0 $
bx #
b0 "
b0 !
$end
#10
b0 #
#11
b1 #
#12
b10 #
b1 !
b1 %
b1 "
b1 $
#13
b11 #
b11 !
b11 %
b10 "
b10 $
#14
b100 #
b0 !
b0 %
b11 "
b11 $
#15
b101 #
b100 "
b100 $
#16
b110 #
b101 "
b101 $
#17
b111 #
b110 "
b110 $
#18
b1000 #
b111 "
b111 $
