rom/rom_reg.v
module rom_reg (
    addr,   // 目标地址
    instruction,    // 取出的指令
);

    input [7: 0] addr;
    output [15: 0] instruction;

    reg[15: 0] rom[255: 0]; // 用于存储读到的指令

    // 初始化，读取init.txt中的指令
    initial $readmemb("./init.txt", rom, 0, 15);

    assign instruction = rom[addr];
endmodule

rom/rom_reg_test.v
`include "./rom/rom_reg.v"

module rom_reg_test ();
    
    wire [15: 0] instruction;

    reg [7: 0] addr;

    rom_reg U_rom_reg(
        .addr(addr),
        .instruction(instruction)
    );
    reg [7: 0] i;

    initial begin
        addr = 8'd0;
        
    end

    initial begin
        #10
        for (i = 0; i < 8'd8; i = i + 1) 
            #1
            addr = i;

        #10
        $finish;
    end
    initial begin            
        $dumpfile("./rom/rom_reg_test.vcd");      
        $dumpvars(0, rom_reg_test);   
    end

endmodule

rom/rom_reg_test.vcd
$date
	Fri May 19 16:58:07 2023
$end
$version
	Icarus Verilog
$end
$timescale
	1s
$end
$scope module rom_reg_test $end
$var wire 16 ! instruction [15:0] $end
$var reg 8 " addr [7:0] $end
$var reg 8 # i [7:0] $end
$scope module U_rom_reg $end
$var wire 8 $ addr [7:0] $end
$var wire 16 % instruction [15:0] $end
$upscope $end
$upscope $end
$enddefinitions $end
$comment Show the parameter values. $end
$dumpall
$end
#0
$dumpvars
b110000001010111 %
b0 $
bx #
b0 "
b110000001010111 !
$end
#10
b0 #
#11
b1 #
#12
b10 #
b1 !
b1 %
b1 "
b1 $
#13
b11 #
b10 !
b10 %
b10 "
b10 $
#14
b100 #
b11 !
b11 %
b11 "
b11 $
#15
b101 #
b100 !
b100 %
b100 "
b100 $
#16
b110 #
b101 !
b101 %
b101 "
b101 $
#17
b111 #
b110 !
b110 %
b110 "
b110 $
#18
b1000 #
b111 !
b111 %
b111 "
b111 $
