pc_reg/pc_reg.v

// ****************************************
// | 信号名 | 位宽 | 输入输出 | 说明                 |
// | ------ | ---- | -------- | -------------------- |
// | clk    | 1b   | input    | 时钟信号             |
// | rst_n  | 1b   | input    | 读出的指令           |

// | pc_out | 8b   | output   | 更新后的pc值         |
// ****************************************

module pc_reg (
    clk,        // 时钟
    rst_n,      // 复位
    pc_out      // 更新后的PC值
);

    input clk;
    input rst_n;

    output reg [7: 0] pc_out;

    always @(posedge clk or negedge rst_n) begin    // 时钟上升沿 或者 复位端被触发
        if (!rst_n)         // 如果复位端被触发
            pc_out <= 8'd0; // 置零
        else
            pc_out <= (pc_out + 1);   // 输出下一个pc值
    end

    initial begin
        pc_out <= 8'd0;
    end

endmodule

pc_reg/pc_reg_test.v
`include "./pc_reg/pc_reg.v"

module pc_reg_test ();
    
    reg clk;
    reg rst_n;
    wire [7: 0] pc_out;

    reg[3: 0] i;

    pc_reg U_pc_reg(
        .clk(clk),
        .rst_n(rst_n),
        .pc_out(pc_out)
    );

    always #0.5 clk <= ~clk;

    initial begin
        clk = 1'b0;
        rst_n = 1'b1;
    
        for (i = 0 ;i < 4'd10 ; i = i + 1) #1;
        #1 rst_n <= ~rst_n;
        #1 rst_n <= ~rst_n;
        for (i = 0 ;i < 4'd10 ; i = i + 1) #1;

        $finish;

    end

    initial begin            
        $dumpfile("pc_reg_test.vcd");      
        $dumpvars(0, pc_reg_test);   
    end

endmodule

pc_reg/pc_reg_test.vcd
$date
	Mon May 22 16:03:24 2023
$end
$version
	Icarus Verilog
$end
$timescale
	1s
$end
$scope module pc_reg_test $end
$var wire 8 ! pc_out [7:0] $end
$var reg 1 " clk $end
$var reg 4 # i [3:0] $end
$var reg 1 $ rst_n $end
$scope module U_pc_reg $end
$var wire 1 " clk $end
$var wire 1 $ rst_n $end
$var reg 8 % pc_out [7:0] $end
$upscope $end
$upscope $end
$enddefinitions $end
$comment Show the parameter values. $end
$dumpall
$end
#0
$dumpvars
b0 %
1$
b0 #
0"
b0 !
$end
#1
b1 !
b1 %
1"
b1 #
#2
0"
b10 #
#3
b10 !
b10 %
1"
b11 #
#4
0"
b100 #
#5
b11 !
b11 %
1"
b101 #
#6
0"
b110 #
#7
b100 !
b100 %
1"
b111 #
#8
0"
b1000 #
#9
b101 !
b101 %
1"
b1001 #
#10
0"
b1010 #
#11
b0 !
b0 %
0$
1"
#12
1$
0"
b0 #
#13
b1 !
b1 %
1"
b1 #
#14
0"
b10 #
#15
b10 !
b10 %
1"
b11 #
#16
0"
b100 #
#17
b11 !
b11 %
1"
b101 #
#18
0"
b110 #
#19
b100 !
b100 %
1"
b111 #
#20
0"
b1000 #
#21
b101 !
b101 %
1"
b1001 #
#22
0"
b1010 #
